{
  "pngResolution": 160,
  "lilypondVersion": "2.18",
  "paperSize": "a4",
  "quarterTempo": 140,
  "pitchClassSequence": [0, 2, 4, 5, 7, 9, 11],
  "numPitchClasses": 12,
  "stepNames": ["c", "d", "e", "f", "g", "a", "b"],
  "degreeNames": ["I", "II", "III", "IV", "V", "VI", "VII"],
  "flatSpelling": "es",
  "sharpSpelling": "is",
  "dotSpelling": ".",
  "qualitySpelling": [
    {"symbol": "M", "chordNotation": "", "degreeNotation": ""},
    {"symbol": "-", "chordNotation": "m", "degreeNotation": "-"},
    {"symbol": "dim", "chordNotation": "dim", "degreeNotation": "b5"},
    {"symbol": "+", "chordNotation": "aug", "degreeNotation": "+"},
    {"symbol": "M7", "chordNotation": "maj7", "degreeNotation": "Δ"},
    {"symbol": "-7", "chordNotation": "min7", "degreeNotation": "-7"},
    {"symbol": "7", "chordNotation": "7", "degreeNotation": "7"},
    {"symbol": "dim7", "chordNotation": "dim7", "degreeNotation": "o"},
    {"symbol": "-7b5", "chordNotation": "3-.5-.7", "degreeNotation": "ø"},
    {"symbol": "+7", "chordNotation": "3.5+.7-", "degreeNotation": "+7"}
  ]
}